Algg/__init__.py
Algg/find.py
Algg/recursion.py
Algg/sort.py
Algg-1.0.3.dist-info/LICENSE
Algg-1.0.3.dist-info/METADATA
Algg-1.0.3.dist-info/WHEEL
Algg-1.0.3.dist-info/top_level.txt
Algg-1.0.3.dist-info/RECORD
